Workbook
Name HostGrowth: Assumptions!$B$33
Name GrowthTokens2027: Assumptions!$C$14
Name ScaleTokens2030: Assumptions!$F$15
Name HostScale: Assumptions!$B$34
Name SetupStarter: Assumptions!$B$25
Name ScaleTokens2028: Assumptions!$D$15
Name RentalRateY1: Assumptions!$B$37
Name StarterTokens2027: Assumptions!$C$13
Name SetupScale: Assumptions!$B$27
Name SetupEnterprise: Assumptions!$B$28
Name RentalRate: Assumptions!$B$37
Name RentalRate_Y1: Assumptions!$B$37
Name GrowthTokens2028: Assumptions!$D$14
Name TokenPrice2026: Assumptions!$B$5
Name StarterTokens2030: Assumptions!$F$13
Name StarterTokens2028: Assumptions!$D$13
Name EnterpriseTokensInit: Assumptions!$B$16
Name TokenPrice2027: Assumptions!$B$6
Name GrowthTokens2030: Assumptions!$F$14
Name GrowthTokens2029: Assumptions!$E$14
Name ScaleTokens2027: Assumptions!$C$15
Name ThresholdReduction: Assumptions!$A$21
Name TokenPrice2031: Assumptions!$B$10
Name SetupGrowth: Assumptions!$B$26
Name EnterpriseTokens2028: Assumptions!$D$16
Name StarterTokens2029: Assumptions!$E$13
Name EnterpriseTokens2029: Assumptions!$E$16
Name HostEnterprise: Assumptions!$B$35
Name TokenPrice2029: Assumptions!$B$8
Name ScaleTokensInit: Assumptions!$B$15
Name HostStarter: Assumptions!$B$32
Name TokenPrice2028: Assumptions!$B$7
Name StarterTokensInit: Assumptions!$B$13
Name TokenPrice2030: Assumptions!$B$9
Name ScaleTokens2029: Assumptions!$E$15
Name RentalRateYn: Assumptions!$B$38
Name EnterpriseTokens2027: Assumptions!$C$16
Name EnterpriseTokens2030: Assumptions!$F$16
Name GrowthTokensInit: Assumptions!$B$14

Sheet Assumptions
A1: Swiss 6022 – Business Model Assumptions (fixed references)
A2: Edit yellow cells to tune the model. Values flow into years & summary. | E2: Cells to be changed
A3: Token prices (€/token) | I3: Pool
A4: Year | B4: €/token (beg of period) | C4: Growth | D4: in | E4: out | F4: solde | G4: New price (end of period) | H4: Market Cap (beg of period) | I4: Market Cap (enf of period) | J4: USD | K4: Price | L4: Asset swiss 6022 | M4: Cash from pool | N4: Swiss 6022 assets Value
A5: 2026 | B5: =K5 | D5: ='2026'!H14 | E5: =0.6*D5 | F5: =D5-E5 | G5: =B5*(1+F5/J5) | H5: =B5*1000000000 | I5: =G5*1000000000 | J5: 75810 | K5: 0.005 | L5: 400000000 | N5: =L5*G5
A6: 2027 | B6: =G5 | C6: =TokenPrice2027/TokenPrice2026-1 | D6: ='2027'!H14 | E6: =0.5*D6 | F6: =D6-E6 | G6: =B6*(1+F6/J$5) | H6: =B6*1000000000 | I6: =G6*1000000000 | J6: =F6+J5 | K6: =G6 | L6: 400000000 | N6: =L6*G6
A7: 2028 | B7: =G6 | C7: =TokenPrice2028/TokenPrice2027-1 | D7: ='2028'!H14 | E7: =0.5*D7 | F7: =D7-E7 | G7: =B7*(1+F7/J$5) | H7: =B7*1000000000 | I7: =G7*1000000000 | J7: =F7+J6 | K7: =G7 | L7: 400000000 | N7: =L7*G7
A8: 2029 | B8: =G7 | C8: =TokenPrice2029/TokenPrice2028-1 | D8: ='2029'!H14 | E8: =0.5*D8 | F8: =D8-E8 | G8: =B8*(1+F8/J$5) | H8: =B8*1000000000 | I8: =G8*1000000000 | J8: =F8+J7 | K8: =G8 | L8: =L7-(M8/K8) | N8: =L8*G8
A9: 2030 | B9: =G8 | C9: =TokenPrice2030/TokenPrice2029-1 | D9: ='2030'!H14 | E9: =0.5*D9 | F9: =D9-E9 | G9: =B9*(1+F9/J$5) | H9: =B9*1000000000 | I9: =G9*1000000000 | J9: =F9+J8 | K9: =G9 | L9: =L8-(M9/K9) | N9: =L9*G9
A10: 2031 | D10: ='2029'!H16
A11: Stake-to-Access thresholds | B11: Nb of tokens | H11: In Euros
A12: Tier | B12: Tokens 2026 | C12: Tokens 2027 | D12: Tokens 2028 | E12: Tokens 2029 | F12: Tokens 2030 | G12: CAGR | H12: Tokens 2026 | I12: Tokens 2027 | J12: Tokens 2028 | K12: Tokens 2029 | L12: Tokens 2030 | M12: CAGR
A13: Starter | B13: 1000000 | C13: =0.5*B13 | D13: =0.5*C13 | E13: =0.5*D13 | F13: =0.5*E13 | G13: =(F13/B13)^(1/4)-1 | H13: =B13*B$5 | I13: =C13*B$6 | J13: =D13*B$7 | K13: =E13*B$8 | L13: =F13*B$9 | M13: =(L13/H13)^(1/4)-1
A14: Growth | B14: 3000000 | C14: =0.5*B14 | D14: =0.5*C14 | E14: =0.5*D14 | F14: =0.5*E14 | G14: =(F14/B14)^(1/4)-1 | H14: =B14*B$5 | I14: =C14*B$6 | J14: =D14*B$7 | K14: =E14*B$8 | L14: =F14*B$9 | M14: =(L14/H14)^(1/4)-1
A15: Scale | B15: 7500000 | C15: =0.5*B15 | D15: =0.5*C15 | E15: =0.5*D15 | F15: =0.5*E15 | G15: =(F15/B15)^(1/4)-1 | H15: =B15*B$5 | I15: =C15*B$6 | J15: =D15*B$7 | K15: =E15*B$8 | L15: =F15*B$9 | M15: =(L15/H15)^(1/4)-1
A16: Enterprise | B16: 9000000 | C16: =0.5*B16 | D16: =0.5*C16 | E16: =0.5*D16 | F16: =0.5*E16 | G16: =(F16/B16)^(1/4)-1 | H16: =B16*B$5 | I16: =C16*B$6 | J16: =D16*B$7 | K16: =E16*B$8 | L16: =F16*B$9 | M16: =(L16/H16)^(1/4)-1
A17: Delta vs PY | C17: =C16/EnterpriseTokensInit-1 | D17: =D16/C16-1 | E17: =E16/D16-1 | F17: =F16/E16-1 | I17: =I15/H15-1 | J17: =J15/I15-1 | K17: =K15/J15-1 | L17: =L15/K15-1
A19: Annual token threshold reduction (to cap cash-entry growth)
A20: Reduction %
A21: 0.1
A23: Pricing – Setup (one-off)
A24: Tier | B24: € / client
A25: Starter | B25: 80000
A26: Growth | B26: 150000
A27: Scale | B27: 200000
A28: Enterprise | B28: 300000
A30: Pricing – Hosting (recurring per year)
A31: Tier | B31: € / client / year | D31: origine
A32: Starter | B32: =3*12000 | D32: 18000
A33: Growth | B33: 60000 | D33: 24000
A34: Scale | B34: 84000 | D34: 36000
A35: Enterprise | B35: =10*12000 | D35: 60000
A37: Rental Rate Y1 | B37: 1
A38: Rental Rate Yn | B38: 0.7

Sheet 2026
A1: Year 2026 – client inputs & revenues
A2: Enter new clients by Tier & Mode. Hosting and Rentals includes carry-over (cumulative clients). | G2: Cells to be changed
A4: Tier | B4: Mode | C4: New Clients | D4: Setup €/client | E4: Hosting €/client/year | F4: Token €/unit | G4: Adjusted Tokens thresholds | H4: Stake €/client | I4: Rental Y1 % | J4: Rental Yn % | K4: Setup Revenue | L4: Hosting Revenue | M4: Rental Revenue Y1 New clients | N4: Total Rental Revenue | O4: Cumulative Clients | P4: Year summary
A5: Starter | B5: Buy | C5: 3 | D5: =SetupStarter | E5: =HostStarter | F5: =TokenPrice2026 | G5: =StarterTokensInit | H5: =F5*G5 | K5: =C5*D5 | L5: =O5*E5 | O5: =2+C5 | P5: Setup revenue | Q5: =K13
A6: Starter | B6: Rent | C6: 3 | D6: =SetupStarter | E6: =HostStarter | F6: =TokenPrice2026 | G6: =StarterTokensInit | H6: =F6*G6 | I6: =RentalRateY1 | J6: =RentalRateYn | K6: =C6*D6 | L6: =O6*E6 | M6: =C6*I6*H6 | N6: =M6+(J6*H6*(O6-C6)) | O6: =0+C6 | P6: Hosting revenue | Q6: =L13 | R6: =(Q7+Q6)/Q8
A7: Growth | B7: Buy | C7: 1 | D7: =SetupGrowth | E7: =HostGrowth | F7: =TokenPrice2026 | G7: =GrowthTokensInit | H7: =F7*G7 | K7: =C7*D7 | L7: =O7*E7 | O7: =0+C7 | P7: Rental revenue | Q7: =N13
A8: Growth | B8: Rent | C8: 1 | D8: =SetupGrowth | E8: =HostGrowth | F8: =TokenPrice2026 | G8: =GrowthTokensInit | H8: =F8*G8 | I8: =RentalRateY1 | J8: =RentalRateYn | K8: =C8*D8 | L8: =O8*E8 | M8: =C8*I8*H8 | N8: =M8+(J8*H8*(O8-C8)) | O8: =0+C8 | P8: Total revenue | Q8: =SUM(Q5:Q7)
A9: Scale | B9: Buy | C9: 0 | D9: =SetupScale | E9: =HostScale | F9: =TokenPrice2026 | G9: =ScaleTokensInit | H9: =F9*G9 | K9: =C9*D9 | L9: =O9*E9 | O9: =0+C9
A10: Scale | B10: Rent | C10: 1 | D10: =SetupScale | E10: =HostScale | F10: =TokenPrice2026 | G10: =ScaleTokensInit | H10: =F10*G10 | I10: =RentalRateY1 | J10: =RentalRateYn | K10: =C10*D10 | L10: =O10*E10 | M10: =C10*I10*H10 | N10: =M10+(J10*H10*(O10-C10)) | O10: =0+C10
A11: Enterprise | B11: Buy | C11: 0 | D11: =SetupEnterprise | E11: =HostEnterprise | F11: =TokenPrice2026 | G11: =EnterpriseTokensInit | H11: =F11*G11 | K11: =C11*D11 | L11: =O11*E11 | O11: =0+C11
A12: Enterprise | B12: Rent | C12: 0 | D12: =SetupEnterprise | E12: =HostEnterprise | F12: =TokenPrice2026 | G12: =EnterpriseTokensInit | H12: =F12*G12 | I12: =RentalRateY1 | J12: =RentalRateYn | K12: =C12*D12 | L12: =O12*E12 | M12: =C12*I12*H12 | N12: =M12+(J12*H12*(O12-C12)) | O12: =0+C12
A13: TOTAL | C13: =SUM(C5:C12) | K13: =SUM(K5:K12) | L13: =SUM(L5:L12) | N13: =SUM(N5:N12) | O13: =SUM(O5:O12)
G14: total injecté dans la pool | H14: =sum(H5:H12)
A15: Rental % clients | C15: =(C6+C8+C12+C10)/C13
A17: Nb of tokens for rental /New clients | C17: =G6*C6+G8*C8+G10*C10+G12*C12
A18: Cumulative Tokens for Rental | C18: =C17

Sheet 2027
A1: Year 2027 – client inputs & revenues
A2: Enter new clients by Tier & Mode. Hosting and Rentals includes carry-over (cumulative clients). | G2: Cells to be changed
A4: Tier | B4: Mode | C4: New Clients | D4: Setup €/client | E4: Hosting €/client/year | F4: Token €/unit | G4: Adjusted Tokens thresholds | H4: Stake €/client | I4: Rental Y1 % | J4: Rental Yn % | K4: Setup Revenue | L4: Hosting Revenue | M4: Rental Revenue Y1 New clients | N4: Total Rental Revenue | O4: Cumulative Clients | P4: Year summary
A5: Starter | B5: Buy | C5: 5 | D5: =SetupStarter | E5: =HostStarter | F5: =TokenPrice2027 | G5: =StarterTokens2027 | H5: =F5*G5 | K5: =C5*D5 | L5: =O5*E5 | O5: ='2026'!$O$5+C5 | P5: Setup revenue | Q5: =K13
A6: Starter | B6: Rent | C6: 5 | D6: =SetupStarter | E6: =HostStarter | F6: =TokenPrice2027 | G6: =StarterTokens2027 | H6: =F6*G6 | I6: =RentalRateY1 | J6: =RentalRateYn | K6: =C6*D6 | L6: =O6*E6 | M6: =C6*I6*H6 | N6: =M6+(J6*H6*(O6-C6)) | O6: ='2026'!$O$6+C6 | P6: Hosting revenue | Q6: =L13 | R6: =(Q7+Q6)/Q8
A7: Growth | B7: Buy | C7: 3 | D7: =SetupGrowth | E7: =HostGrowth | F7: =TokenPrice2027 | G7: {=GrowthTokens2027} | H7: =F7*G7 | K7: =C7*D7 | L7: =O7*E7 | O7: ='2026'!$O$7+C7 | P7: Rental revenue | Q7: =N13
A8: Growth | B8: Rent | C8: 3 | D8: =SetupGrowth | E8: =HostGrowth | F8: =TokenPrice2027 | G8: {=GrowthTokens2027} | H8: =F8*G8 | I8: =RentalRateY1 | J8: =RentalRateYn | K8: =C8*D8 | L8: =O8*E8 | M8: =C8*I8*H8 | N8: =M8+(J8*H8*(O8-C8)) | O8: ='2026'!$O$8+C8 | P8: Total revenue | Q8: =SUM(Q5:Q7)
A9: Scale | B9: Buy | C9: 1 | D9: =SetupScale | E9: =HostScale | F9: =TokenPrice2027 | G9: =ScaleTokens2027 | H9: =F9*G9 | K9: =C9*D9 | L9: =O9*E9 | O9: ='2026'!$O$9+C9
A10: Scale | B10: Rent | C10: 2 | D10: =SetupScale | E10: =HostScale | F10: =TokenPrice2027 | G10: =ScaleTokens2027 | H10: =F10*G10 | I10: =RentalRateY1 | J10: =RentalRateYn | K10: =C10*D10 | L10: =O10*E10 | M10: =C10*I10*H10 | N10: =M10+(J10*H10*(O10-C10)) | O10: ='2026'!$O$10+C10
A11: Enterprise | B11: Buy | C11: 0 | D11: =SetupEnterprise | E11: =HostEnterprise | F11: =TokenPrice2027 | G11: =EnterpriseTokens2027 | H11: =F11*G11 | K11: =C11*D11 | L11: =O11*E11 | O11: ='2026'!$O$11+C11
A12: Enterprise | B12: Rent | C12: 1 | D12: =SetupEnterprise | E12: =HostEnterprise | F12: =TokenPrice2027 | G12: =EnterpriseTokens2027 | H12: =F12*G12 | I12: =RentalRateY1 | J12: =RentalRateYn | K12: =C12*D12 | L12: =O12*E12 | M12: =C12*I12*H12 | N12: =M12+(J12*H12*(O12-C12)) | O12: ='2026'!$O$12+C12
A13: TOTAL | C13: =SUM(C5:C12) | K13: =SUM(K5:K12) | L13: =SUM(L5:L12) | N13: =SUM(N5:N12) | O13: =SUM(O5:O12)
G14: total injecté dans la pool | H14: =sum(H5:H12)
A15: Rental % clients | C15: =(C6+C8+C12+C10)/C13 | O15: =(O6+O8+O12+O10)/O13
A17: Nb of tokens for rental /New clients | C17: =G6*C6+G8*C8+G10*C10+G12*C12
A18: Cumulative Tokens for Rental | C18: =C17+'2026'!C18

Sheet 2028
A1: Year 2028 – client inputs & revenues
A2: Enter new clients by Tier & Mode. Hosting and Rentals includes carry-over (cumulative clients). | G2: Cells to be changed
A4: Tier | B4: Mode | C4: New Clients | D4: Setup €/client | E4: Hosting €/client/year | F4: Token €/unit | G4: Adjusted Tokens thresholds | H4: Stake €/client | I4: Rental Y1 % | J4: Rental Yn % | K4: Setup Revenue | L4: Hosting Revenue | M4: Rental Revenue Y1 New clients | N4: Total Rental Revenue | O4: Cumulative Clients | P4: Year summary
A5: Starter | B5: Buy | C5: 10 | D5: =SetupStarter | E5: =HostStarter | F5: =TokenPrice2028 | G5: =StarterTokens2028 | H5: =F5*G5 | K5: =C5*D5 | L5: =O5*E5 | O5: ='2027'!$O$5+C5 | P5: Setup revenue | Q5: =K13
A6: Starter | B6: Rent | C6: 10 | D6: =SetupStarter | E6: =HostStarter | F6: =TokenPrice2028 | G6: =StarterTokens2028 | H6: =F6*G6 | I6: =RentalRateY1 | J6: =RentalRateYn | K6: =C6*D6 | L6: =O6*E6 | M6: =C6*I6*H6 | N6: =M6+(J6*H6*(O6-C6)) | O6: ='2027'!$O$6+C6 | P6: Hosting revenue | Q6: =L13 | R6: =(Q7+Q6)/Q8
A7: Growth | B7: Buy | C7: 5 | D7: =SetupGrowth | E7: =HostGrowth | F7: =TokenPrice2028 | G7: =GrowthTokens2028 | H7: =F7*G7 | K7: =C7*D7 | L7: =O7*E7 | O7: ='2027'!$O$7+C7 | P7: Rental revenue | Q7: =N13
A8: Growth | B8: Rent | C8: 5 | D8: =SetupGrowth | E8: =HostGrowth | F8: =TokenPrice2028 | G8: =GrowthTokens2028 | H8: =F8*G8 | I8: =RentalRateY1 | J8: =RentalRateYn | K8: =C8*D8 | L8: =O8*E8 | M8: =C8*I8*H8 | N8: =M8+(J8*H8*(O8-C8)) | O8: ='2027'!$O$8+C8 | P8: Total revenue | Q8: =SUM(Q5:Q7)
A9: Scale | B9: Buy | C9: 2 | D9: =SetupScale | E9: =HostScale | F9: =TokenPrice2028 | G9: =ScaleTokens2028 | H9: =F9*G9 | K9: =C9*D9 | L9: =O9*E9 | O9: ='2027'!$O$9+C9
A10: Scale | B10: Rent | C10: 4 | D10: =SetupScale | E10: =HostScale | F10: =TokenPrice2028 | G10: =ScaleTokens2028 | H10: =F10*G10 | I10: =RentalRateY1 | J10: =RentalRateYn | K10: =C10*D10 | L10: =O10*E10 | M10: =C10*I10*H10 | N10: =M10+(J10*H10*(O10-C10)) | O10: ='2027'!$O$10+C10
A11: Enterprise | B11: Buy | C11: 2 | D11: =SetupEnterprise | E11: =HostEnterprise | F11: =TokenPrice2028 | G11: =EnterpriseTokens2028 | H11: =F11*G11 | K11: =C11*D11 | L11: =O11*E11 | O11: ='2027'!$O$11+C11
A12: Enterprise | B12: Rent | C12: 2 | D12: =SetupEnterprise | E12: =HostEnterprise | F12: =TokenPrice2028 | G12: =EnterpriseTokens2028 | H12: =F12*G12 | I12: =RentalRateY1 | J12: =RentalRateYn | K12: =C12*D12 | L12: =O12*E12 | M12: =C12*I12*H12 | N12: =M12+(J12*H12*(O12-C12)) | O12: ='2027'!$O$12+C12
A13: TOTAL | C13: =SUM(C5:C12) | K13: =SUM(K5:K12) | L13: =SUM(L5:L12) | N13: =SUM(N5:N12) | O13: =SUM(O5:O12)
G14: total injecté dans la pool | H14: =sum(H5:H12)
A15: Rental % clients | C15: =(C6+C8+C12+C10)/C13
A17: Nb of tokens for rental /New clients | C17: =G6*C6+G8*C8+G10*C10+G12*C12
A18: Cumulative Tokens for Rental | C18: =C17+'2027'!C18

Sheet 2029
A1: Year 2029 – client inputs & revenues
A2: Enter new clients by Tier & Mode. Hosting and Rentals includes carry-over (cumulative clients). | G2: Cells to be changed
A4: Tier | B4: Mode | C4: New Clients | D4: Setup €/client | E4: Hosting €/client/year | F4: Token €/unit | G4: Adjusted Tokens thresholds | H4: Stake €/client | I4: Rental Y1 % | J4: Rental Yn % | K4: Setup Revenue | L4: Hosting Revenue | M4: Rental Revenue Y1 New clients | N4: Total Rental Revenue | O4: Cumulative Clients | P4: Year summary
A5: Starter | B5: Buy | C5: 15 | D5: =SetupStarter | E5: =HostStarter | F5: =TokenPrice2029 | G5: =StarterTokens2029 | H5: =F5*G5 | K5: =C5*D5 | L5: =O5*E5 | O5: ='2028'!$O$5+C5 | P5: Setup revenue | Q5: =K13
A6: Starter | B6: Rent | C6: 15 | D6: =SetupStarter | E6: =HostStarter | F6: =TokenPrice2029 | G6: =StarterTokens2029 | H6: =F6*G6 | I6: =RentalRateY1 | J6: =RentalRateYn | K6: =C6*D6 | L6: =O6*E6 | M6: =C6*I6*H6 | N6: =M6+(J6*H6*(O6-C6)) | O6: ='2028'!$O$6+C6 | P6: Hosting revenue | Q6: =L13 | R6: =(Q7+Q6)/Q8
A7: Growth | B7: Buy | C7: 10 | D7: =SetupGrowth | E7: =HostGrowth | F7: =TokenPrice2029 | G7: =GrowthTokens2029 | H7: =F7*G7 | K7: =C7*D7 | L7: =O7*E7 | O7: ='2028'!$O$7+C7 | P7: Rental revenue | Q7: =N13
A8: Growth | B8: Rent | C8: 10 | D8: =SetupGrowth | E8: =HostGrowth | F8: =TokenPrice2029 | G8: =GrowthTokens2029 | H8: =F8*G8 | I8: =RentalRateY1 | J8: =RentalRateYn | K8: =C8*D8 | L8: =O8*E8 | M8: =C8*I8*H8 | N8: =M8+(J8*H8*(O8-C8)) | O8: ='2028'!$O$8+C8 | P8: Total revenue | Q8: =SUM(Q5:Q7)
A9: Scale | B9: Buy | C9: 5 | D9: =SetupScale | E9: =HostScale | F9: =TokenPrice2029 | G9: =ScaleTokens2029 | H9: =F9*G9 | K9: =C9*D9 | L9: =O9*E9 | O9: ='2028'!$O$9+C9
A10: Scale | B10: Rent | C10: 5 | D10: =SetupScale | E10: =HostScale | F10: =TokenPrice2029 | G10: =ScaleTokens2029 | H10: =F10*G10 | I10: =RentalRateY1 | J10: =RentalRateYn | K10: =C10*D10 | L10: =O10*E10 | M10: =C10*I10*H10 | N10: =M10+(J10*H10*(O10-C10)) | O10: ='2028'!$O$10+C10
A11: Enterprise | B11: Buy | C11: 3 | D11: =SetupEnterprise | E11: =HostEnterprise | F11: =TokenPrice2029 | G11: =EnterpriseTokens2029 | H11: =F11*G11 | K11: =C11*D11 | L11: =O11*E11 | O11: ='2028'!$O$11+C11
A12: Enterprise | B12: Rent | C12: 3 | D12: =SetupEnterprise | E12: =HostEnterprise | F12: =TokenPrice2029 | G12: =EnterpriseTokens2029 | H12: =F12*G12 | I12: =RentalRateY1 | J12: =RentalRateYn | K12: =C12*D12 | L12: =O12*E12 | M12: =C12*I12*H12 | N12: =M12+(J12*H12*(O12-C12)) | O12: ='2028'!$O$12+C12
A13: TOTAL | C13: =SUM(C5:C12) | K13: =SUM(K5:K12) | L13: =SUM(L5:L12) | N13: =SUM(N5:N12) | O13: =SUM(O5:O12)
G14: total injecté dans la pool | H14: =sum(H5:H12)
A15: Rental % clients | C15: =(C6+C8+C12+C10)/C13
A17: Nb of tokens for rental /New clients | C17: =G6*C6+G8*C8+G10*C10+G12*C12
A18: Cumulative Tokens for Rental | C18: =C17+'2028'!C18

Sheet 2030
A1: Year 2030 – client inputs & revenues
A2: Enter new clients by Tier & Mode. Hosting and Rentals includes carry-over (cumulative clients). | G2: Cells to be changed
A4: Tier | B4: Mode | C4: New Clients | D4: Setup €/client | E4: Hosting €/client/year | F4: Token €/unit | G4: Adjusted Tokens thresholds | H4: Stake €/client | I4: Rental Y1 % | J4: Rental Yn % | K4: Setup Revenue | L4: Hosting Revenue | M4: Rental Revenue Y1 New clients | N4: Total Rental Revenue | O4: Cumulative Clients | P4: Year summary
A5: Starter | B5: Buy | C5: 20 | D5: =SetupStarter | E5: =HostStarter | F5: =TokenPrice2030 | G5: =StarterTokens2030 | H5: =F5*G5 | K5: =C5*D5 | L5: =O5*E5 | O5: ='2029'!$O$5+C5 | P5: Setup revenue | Q5: =K13
A6: Starter | B6: Rent | C6: 20 | D6: =SetupStarter | E6: =HostStarter | F6: =TokenPrice2030 | G6: =StarterTokens2030 | H6: =F6*G6 | I6: =RentalRateY1 | J6: =RentalRateYn | K6: =C6*D6 | L6: =O6*E6 | M6: =C6*I6*H6 | N6: =M6+(J6*H6*(O6-C6)) | O6: ='2029'!$O$6+C6 | P6: Hosting revenue | Q6: =L13 | R6: =(Q7+Q6)/Q8
A7: Growth | B7: Buy | C7: 15 | D7: =SetupGrowth | E7: =HostGrowth | F7: =TokenPrice2030 | G7: =GrowthTokens2030 | H7: =F7*G7 | K7: =C7*D7 | L7: =O7*E7 | O7: ='2029'!$O$7+C7 | P7: Rental revenue | Q7: =N13
A8: Growth | B8: Rent | C8: 15 | D8: =SetupGrowth | E8: =HostGrowth | F8: =TokenPrice2030 | G8: =GrowthTokens2030 | H8: =F8*G8 | I8: =RentalRateY1 | J8: =RentalRateYn | K8: =C8*D8 | L8: =O8*E8 | M8: =C8*I8*H8 | N8: =M8+(J8*H8*(O8-C8)) | O8: ='2029'!$O$8+C8 | P8: Total revenue | Q8: =SUM(Q5:Q7)
A9: Scale | B9: Buy | C9: 10 | D9: =SetupScale | E9: =HostScale | F9: =TokenPrice2030 | G9: =ScaleTokens2030 | H9: =F9*G9 | K9: =C9*D9 | L9: =O9*E9 | O9: ='2029'!$O$9+C9
A10: Scale | B10: Rent | C10: 10 | D10: =SetupScale | E10: =HostScale | F10: =TokenPrice2030 | G10: =ScaleTokens2030 | H10: =F10*G10 | I10: =RentalRateY1 | J10: =RentalRateYn | K10: =C10*D10 | L10: =O10*E10 | M10: =C10*I10*H10 | N10: =M10+(J10*H10*(O10-C10)) | O10: ='2029'!$O$10+C10
A11: Enterprise | B11: Buy | C11: 5 | D11: =SetupEnterprise | E11: =HostEnterprise | F11: =TokenPrice2030 | G11: =EnterpriseTokens2030 | H11: =F11*G11 | K11: =C11*D11 | L11: =O11*E11 | O11: ='2029'!$O$11+C11
A12: Enterprise | B12: Rent | C12: 5 | D12: =SetupEnterprise | E12: =HostEnterprise | F12: =TokenPrice2030 | G12: =EnterpriseTokens2030 | H12: =F12*G12 | I12: =RentalRateY1 | J12: =RentalRateYn | K12: =C12*D12 | L12: =O12*E12 | M12: =C12*I12*H12 | N12: =M12+(J12*H12*(O12-C12)) | O12: ='2029'!$O$12+C12
A13: TOTAL | C13: =SUM(C5:C12) | K13: =SUM(K5:K12) | L13: =SUM(L5:L12) | N13: =SUM(N5:N12) | O13: =SUM(O5:O12)
H14: =sum(H5:H12)
A15: Rental % clients | C15: =(C6+C8+C12+C10)/C13
A17: Nb of tokens for rental /New clients | C17: =G6*C6+G8*C8+G10*C10+G12*C12
A18: Cumulative Tokens for Rental | C18: =C17+'2029'!C18

Sheet Summary
A1: Revenue summary & token trajectory (2026–2030) - With 80% rent
A3: Year | B3: Total Clients | C3: Setup (€) | D3: Hosting (€) | E3: Rental (€) | F3: Total (€) | G3: Recurring % | H3: Token €/unit | I3: Market Cap (1B tokens, €)
A4: 2026 | B4: ='2026'!O13 | C4: ='2026'!$Q$5 | D4: ='2026'!$Q$6 | E4: ='2026'!$Q$7 | F4: =SUM(C4:E4) | G4: =IFERROR((D4+E4)/F4,0) | H4: =TokenPrice2026 | I4: =1000000000*H4
A5: 2027 | B5: ='2027'!O13 | C5: ='2027'!$Q$5 | D5: ='2027'!$Q$6 | E5: ='2027'!$Q$7 | F5: =SUM(C5:E5) | G5: =IFERROR((D5+E5)/F5,0) | H5: =TokenPrice2027 | I5: =1000000000*H5
A6: 2028 | B6: ='2028'!O13 | C6: ='2028'!$Q$5 | D6: ='2028'!$Q$6 | E6: ='2028'!$Q$7 | F6: =SUM(C6:E6) | G6: =IFERROR((D6+E6)/F6,0) | H6: =TokenPrice2028 | I6: =1000000000*H6
A7: 2029 | B7: ='2029'!O13 | C7: ='2029'!$Q$5 | D7: ='2029'!$Q$6 | E7: ='2029'!$Q$7 | F7: =SUM(C7:E7) | G7: =IFERROR((D7+E7)/F7,0) | H7: =TokenPrice2029 | I7: =1000000000*H7
A8: 2030 | B8: ='2030'!O13 | C8: ='2030'!$Q$5 | D8: ='2030'!$Q$6 | E8: ='2030'!$Q$7 | F8: =SUM(C8:E8) | G8: =IFERROR((D8+E8)/F8,0) | H8: =TokenPrice2030 | I8: =1000000000*H8
A9: TOTAL | B9: =B8 | C9: =SUM(C4:C8) | D9: =SUM(D4:D8) | E9: =SUM(E4:E8) | F9: =SUM(F4:F8) | G9: =IFERROR((D9+E9)/F9,0)

Sheet Guide
A1: How to use this simulator
A3: 1) Update token prices, thresholds and pricing in 'Assumptions'.
A4: 2) Year tabs are pre-populated with mixes from Business Model Summary V10 (you can overwrite).
A5: 3) 'Summary' aggregates revenues, recurring %, and token trajectory.
A7: Notes:
A8: • Adjusted tokens per year = Initial tokens × (1 – threshold reduction)^years since 2026.
A9: • Hosting revenue = cumulative clients × annual hosting fee.
A10: • Rental revenue = new Rent clients × rental rate × stake value (onboarding year).
